stresstest/__main__.py
stresstest/errors.py
stresstest/runner.py
stresstest/sensors.py
stresstest/stresstest.py
stresstest/stresstests/__init__.py
stresstest/stresstests/compute/__init__.py
stresstest/stresstests/compute/factorization.py
stresstest/stresstests/compute/fluid_dynamics.py
stresstest/stresstests/compute/hashlib.py
stresstest/stresstests/compute/n_body.py
stresstest/stresstests/compute/pi_digits.py
stresstest/stresstests/interpreter/__init__.py
stresstest/stresstests/interpreter/dict_class.py
stresstest/stresstests/interpreter/random_module.py
stresstest/stresstests/io/__init__.py
stresstest/stresstests/os/__init__.py
stresstest-1.0.0.dist-info/entry_points.txt
stresstest-1.0.0.dist-info/LICENSE
stresstest-1.0.0.dist-info/WHEEL
stresstest-1.0.0.dist-info/METADATA
stresstest-1.0.0.dist-info/RECORD
