Metadata-Version: 2.1
Name: stresstest
Version: 1.0.0
Summary: Stress test your system and Python interpreter.
License: AGPL
Author: Tomas Krejci
Author-email: tomas@krej.ci
Requires-Python: >=3.7,<4.0.0
Classifier: License :: Other/Proprietary License
Classifier: Programming Language :: Python :: 3
Classifier: Programming Language :: Python :: 3.10
Classifier: Programming Language :: Python :: 3.7
Classifier: Programming Language :: Python :: 3.8
Classifier: Programming Language :: Python :: 3.9
Requires-Dist: requests
Requires-Dist: rich
